bark_mcp/__init__.py
bark_mcp/cli.py
bark_mcp/server.py
bark_mcp-0.1.2.dist-info/licenses/LICENSE
bark_mcp-0.1.2.dist-info/METADATA
bark_mcp-0.1.2.dist-info/WHEEL
bark_mcp-0.1.2.dist-info/entry_points.txt
bark_mcp-0.1.2.dist-info/top_level.txt
bark_mcp-0.1.2.dist-info/RECORD
