Metadata-Version: 2.4
Name: bark-mcp
Version: 0.1.2
Summary: MCP server talking to Bark notification server for iOS
Author: Bark MCP Contributors
License: MIT License
Project-URL: Homepage, https://github.com/yourusername/bark-mcp
Project-URL: Bug Tracker, https://github.com/yourusername/bark-mcp/issues
Classifier: Programming Language :: Python :: 3
Classifier: License :: OSI Approved :: MIT License
Classifier: Operating System :: OS Independent
Requires-Python: >=3.8
License-File: LICENSE
Requires-Dist: fastmcp>=2.0.0
Requires-Dist: requests>=2.28.0
Requires-Dist: python-dotenv>=1.0.0
Dynamic: license-file
